pgcaw/__init__.py
pgcaw/contributions.py
pgcaw-1.0.1.dist-info/LICENSE.txt
pgcaw-1.0.1.dist-info/METADATA
pgcaw-1.0.1.dist-info/WHEEL
pgcaw-1.0.1.dist-info/top_level.txt
pgcaw-1.0.1.dist-info/RECORD
