Metadata-Version: 2.1
Name: pgcaw
Version: 1.0.1
Summary: PGCAW is a very simple API wrapper for the github contributions calendar.
Home-page: https://github.com/CGodiksen/pgcaw
Author: Christian Godiksen
Author-email: christian.godiksen55@gmail.com
License: UNKNOWN
Keywords: Github calendar,Github contributions,API,API Wrapper,Github
Platform: UNKNOWN
Classifier: Development Status :: 4 - Beta
Classifier: Intended Audience :: Developers
Classifier: Programming Language :: Python :: 3
Classifier: License :: OSI Approved :: MIT License
Classifier: Operating System :: OS Independent
Requires-Python: >=3.6
Requires-Dist: requests
Requires-Dist: bs4
